L0572017EN6510120170303EN0006651662<p xmlns="http://docs.oasis-open.org/legaldocml/ns/akn/3.0">Corrigendum to Regulation (EU) 2016/429 of the European Parliament and of the Council of 9 March 2016 on transmissible animal diseases and amending and repealing certain acts in the area of animal health (&apos;Animal Health Law&apos;)</p>
<p xmlns="http://docs.oasis-open.org/legaldocml/ns/akn/3.0">(Official Journal of the European Union L 84 of 31 March 2016)</p>
<num xmlns="http://docs.oasis-open.org/legaldocml/ns/akn/3.0">1.</num>
<p xmlns="http://docs.oasis-open.org/legaldocml/ns/akn/3.0">On page 39, Article 14(1), point (c)(i), second indent:</p>
<p xmlns="http://docs.oasis-open.org/legaldocml/ns/akn/3.0"><!--default P | TXT -->for:</p>
<mod xmlns="http://docs.oasis-open.org/legaldocml/ns/akn/3.0">
   <quotedStructure startQuote="" endQuote="">
      <p><!--default P | TXT -->&apos;… as regards activities listed in Article 61, points (a), (b), (e), (f) and (i) of Article 65(1), Article 70(1), Articles 79 and 80, and Article 81(1) and (2), and …&apos;,</p>
   </quotedStructure>
</mod>
<p xmlns="http://docs.oasis-open.org/legaldocml/ns/akn/3.0"><!--default P | TXT -->read:</p>
<mod xmlns="http://docs.oasis-open.org/legaldocml/ns/akn/3.0">
   <quotedStructure startQuote="" endQuote="">
      <p><!--default P | TXT -->&apos;… as regards activities listed in Article 61, points (a), (b), (e), (f) and (i) of Article 65(1), Article 70(1), Articles 79, 80, 81 and 82, and …&apos;.</p>
   </quotedStructure>
</mod>
<num xmlns="http://docs.oasis-open.org/legaldocml/ns/akn/3.0">2.</num>
<p xmlns="http://docs.oasis-open.org/legaldocml/ns/akn/3.0">On page 103, Article 149(1), point (b):</p>
<p xmlns="http://docs.oasis-open.org/legaldocml/ns/akn/3.0"><!--default P | TXT -->for:</p>
<mod xmlns="http://docs.oasis-open.org/legaldocml/ns/akn/3.0">
   <quotedStructure startQuote="" endQuote="">
      <list>
         <point>
            <num>&apos;(b)</num>
            <p>those provided for in delegated acts adopted pursuant to Articles 125(2) and 131(1), Article 135, Articles 136(2), 137(2), 138(4) and 139(4) and Article 140;&apos;,</p>
         </point>
      </list>
   </quotedStructure>
</mod>
<p xmlns="http://docs.oasis-open.org/legaldocml/ns/akn/3.0"><!--default P | TXT -->read:</p>
<mod xmlns="http://docs.oasis-open.org/legaldocml/ns/akn/3.0">
   <quotedStructure startQuote="" endQuote="">
      <list>
         <point>
            <num>&apos;(b)</num>
            <p>those provided for in delegated acts adopted pursuant to Articles 125(2) and 131(1), Article 135, Articles 136(2), 137(2), 138(3) and 139(4) and Article 140;&apos;.</p>
         </point>
      </list>
   </quotedStructure>
</mod>
<num xmlns="http://docs.oasis-open.org/legaldocml/ns/akn/3.0">3.</num>
<p xmlns="http://docs.oasis-open.org/legaldocml/ns/akn/3.0">On page 134, Article 209, title:</p>
<p xmlns="http://docs.oasis-open.org/legaldocml/ns/akn/3.0"><!--default P | TXT -->for:</p>
<mod xmlns="http://docs.oasis-open.org/legaldocml/ns/akn/3.0">
   <quotedStructure startQuote="" endQuote="">
      <p><!--default P | TXT -->&apos;Obligation of operators to ensure that other aquatic animals are accompanied by an animal health certificate and implementing power&apos;,</p>
   </quotedStructure>
</mod>
<p xmlns="http://docs.oasis-open.org/legaldocml/ns/akn/3.0"><!--default P | TXT -->read:</p>
<mod xmlns="http://docs.oasis-open.org/legaldocml/ns/akn/3.0">
   <quotedStructure startQuote="" endQuote="">
      <p><!--default P | TXT -->&apos;Obligation of operators to ensure that other aquatic animals are accompanied by an animal health certificate&apos;.</p>
   </quotedStructure>
</mod>
<num xmlns="http://docs.oasis-open.org/legaldocml/ns/akn/3.0">4.</num>
<p xmlns="http://docs.oasis-open.org/legaldocml/ns/akn/3.0">On page 138, Article 219(1), point (a):</p>
<p xmlns="http://docs.oasis-open.org/legaldocml/ns/akn/3.0"><!--default P | TXT -->for:</p>
<mod xmlns="http://docs.oasis-open.org/legaldocml/ns/akn/3.0">
   <quotedStructure startQuote="" endQuote="">
      <p><!--default P | TXT -->&apos;… and any rules adopted pursuant to Article 211 and Article 214(2);&apos;,</p>
   </quotedStructure>
</mod>
<p xmlns="http://docs.oasis-open.org/legaldocml/ns/akn/3.0"><!--default P | TXT -->read:</p>
<mod xmlns="http://docs.oasis-open.org/legaldocml/ns/akn/3.0">
   <quotedStructure startQuote="" endQuote="">
      <p><!--default P | TXT -->&apos;… and any rules adopted pursuant to Articles 211 and 214;&apos;.</p>
   </quotedStructure>
</mod>
<num xmlns="http://docs.oasis-open.org/legaldocml/ns/akn/3.0">5.</num>
<p xmlns="http://docs.oasis-open.org/legaldocml/ns/akn/3.0">On page 138, Article 219(1), point (b):</p>
<p xmlns="http://docs.oasis-open.org/legaldocml/ns/akn/3.0"><!--default P | TXT -->for:</p>
<mod xmlns="http://docs.oasis-open.org/legaldocml/ns/akn/3.0">
   <quotedStructure startQuote="" endQuote="">
      <p><!--default P | TXT -->&apos;… when they are being moved from a restricted zone as referred to in Article point (a) of 208(2);&apos;,</p>
   </quotedStructure>
</mod>
<p xmlns="http://docs.oasis-open.org/legaldocml/ns/akn/3.0"><!--default P | TXT -->read:</p>
<mod xmlns="http://docs.oasis-open.org/legaldocml/ns/akn/3.0">
   <quotedStructure startQuote="" endQuote="">
      <p><!--default P | TXT -->&apos;… when they are being moved from a restricted zone as referred to in Article 208(2);&apos;.</p>
   </quotedStructure>
</mod>
<num xmlns="http://docs.oasis-open.org/legaldocml/ns/akn/3.0">6.</num>
<p xmlns="http://docs.oasis-open.org/legaldocml/ns/akn/3.0">On page 140, Article 223(1), point (b)(i):</p>
<p xmlns="http://docs.oasis-open.org/legaldocml/ns/akn/3.0"><!--default P | TXT -->for:</p>
<mod xmlns="http://docs.oasis-open.org/legaldocml/ns/akn/3.0">
   <quotedStructure startQuote="" endQuote="">
      <p><!--default P | TXT -->&apos;… point (a) of Article 61(1), Articles 62(1) and 63(1), point (c) of Article 65(1), …&apos;,</p>
   </quotedStructure>
</mod>
<p xmlns="http://docs.oasis-open.org/legaldocml/ns/akn/3.0"><!--default P | TXT -->read:</p>
<mod xmlns="http://docs.oasis-open.org/legaldocml/ns/akn/3.0">
   <quotedStructure startQuote="" endQuote="">
      <p><!--default P | TXT -->&apos;… point (a) of Article 61(1), Article 62(1), point (c) of Article 65(1), …&apos;.</p>
   </quotedStructure>
</mod>
<num xmlns="http://docs.oasis-open.org/legaldocml/ns/akn/3.0">7.</num>
<p xmlns="http://docs.oasis-open.org/legaldocml/ns/akn/3.0">On page 164, Article 264(3):</p>
<p xmlns="http://docs.oasis-open.org/legaldocml/ns/akn/3.0"><!--default P | TXT -->for:</p>
<mod xmlns="http://docs.oasis-open.org/legaldocml/ns/akn/3.0">
   <quotedStructure startQuote="" endQuote="">
      <paragraph>
         <num>&apos;3.</num>
         <content>
            <p>The power to adopt delegated acts referred to in Articles 3(5), 5(2) 5(4), 14(3), … 42(6), 47, 48(3), … 109(2), 118, 119, 122(1), …. 161(6), 162(4),&apos;,</p>
         </content>
      </paragraph>
   </quotedStructure>
</mod>
<p xmlns="http://docs.oasis-open.org/legaldocml/ns/akn/3.0"><!--default P | TXT -->read:</p>
<mod xmlns="http://docs.oasis-open.org/legaldocml/ns/akn/3.0">
   <quotedStructure startQuote="" endQuote="">
      <paragraph>
         <num>&apos;3.</num>
         <content>
            <p>The power to adopt delegated acts referred to in Articles 3(5), 5(2), 5(4), 14(3), … 42(6), 47(1), 48(3), … 109(2), 118(1), 118(2), 119(1), 122(1), … 161(6), 162(3), 162(4),…..&apos;.</p>
         </content>
      </paragraph>
   </quotedStructure>
</mod>
<num xmlns="http://docs.oasis-open.org/legaldocml/ns/akn/3.0">8.</num>
<p xmlns="http://docs.oasis-open.org/legaldocml/ns/akn/3.0">On page 167, Article 271(2), second subparagraph:</p>
<p xmlns="http://docs.oasis-open.org/legaldocml/ns/akn/3.0"><!--default P | TXT -->for:</p>
<mod xmlns="http://docs.oasis-open.org/legaldocml/ns/akn/3.0">
   <quotedStructure startQuote="" endQuote="">
      <p><!--default P | TXT -->&apos;… and the implementing acts provided for in Article 118 of this Regulation.&apos;,</p>
   </quotedStructure>
</mod>
<p xmlns="http://docs.oasis-open.org/legaldocml/ns/akn/3.0"><!--default P | TXT -->read:</p>
<mod xmlns="http://docs.oasis-open.org/legaldocml/ns/akn/3.0">
   <quotedStructure startQuote="" endQuote="">
      <p><!--default P | TXT -->&apos;… and the implementing acts provided for in Article 120 of this Regulation.&apos;.</p>
   </quotedStructure>
</mod>
<num xmlns="http://docs.oasis-open.org/legaldocml/ns/akn/3.0">9.</num>
<p xmlns="http://docs.oasis-open.org/legaldocml/ns/akn/3.0">On page 168, Article 274:</p>
<p xmlns="http://docs.oasis-open.org/legaldocml/ns/akn/3.0"><!--default P | TXT -->for:</p>
<mod xmlns="http://docs.oasis-open.org/legaldocml/ns/akn/3.0">
   <quotedStructure startQuote="" endQuote="">
      <p><!--default P | TXT -->&apos;…. the Commission shall adopt the delegated acts referred to in … Article 122(2), and Articles … 239(1), and …..&apos;,</p>
   </quotedStructure>
</mod>
<p xmlns="http://docs.oasis-open.org/legaldocml/ns/akn/3.0"><!--default P | TXT -->read:</p>
<mod xmlns="http://docs.oasis-open.org/legaldocml/ns/akn/3.0">
   <quotedStructure startQuote="" endQuote="">
      <p><!--default P | TXT -->&apos;… the Commission shall adopt the delegated acts referred to in …. Article 122(1), and Articles … 239(2), and .….&apos;.</p>
   </quotedStructure>
</mod>
