L1472021EN2310120200525EN0009231242<p xmlns="http://docs.oasis-open.org/legaldocml/ns/akn/3.0">Corrigendum to Regulation (EU) 2020/740 of the European Parliament and of the Council of 25 May 2020 on the labelling of tyres with respect to fuel efficiency and other parameters, amending Regulation (EU) 2017/1369 and repealing Regulation (EC) No 1222/2009</p>
<p xmlns="http://docs.oasis-open.org/legaldocml/ns/akn/3.0">(Official Journal of the European Union L 177 of 5 June 2020)</p>
<num xmlns="http://docs.oasis-open.org/legaldocml/ns/akn/3.0">(1)</num>
<p xmlns="http://docs.oasis-open.org/legaldocml/ns/akn/3.0">In the table of contents and on page 1, title:</p>
<p xmlns="http://docs.oasis-open.org/legaldocml/ns/akn/3.0"><!--default P | TXT -->for:</p>
<mod xmlns="http://docs.oasis-open.org/legaldocml/ns/akn/3.0">
   <quotedStructure startQuote="" endQuote="">
      <p><!--default P | TXT -->&apos;Regulation (EU) 2020/740 of the European Parliament and of the Council of 25 May 2020 on the labelling of tyres with respect to fuel efficiency and other parameters, amending Regulation (EU) 2017/1369 and repealing Regulation (EC) No 1222/2009&apos;,</p>
   </quotedStructure>
</mod>
<p xmlns="http://docs.oasis-open.org/legaldocml/ns/akn/3.0"><!--default P | TXT -->read:</p>
<mod xmlns="http://docs.oasis-open.org/legaldocml/ns/akn/3.0">
   <quotedStructure startQuote="" endQuote="">
      <p><!--default P | TXT -->&apos;Regulation (EU) 2020/740 of the European Parliament and of the Council of 25 May 2020 on the labelling of tyres with respect to fuel efficiency and other parameters, amending Regulation (EU) 2017/1369 and repealing Regulation (EC) No 1222/2009 (Text with EEA relevance)&apos;.</p>
   </quotedStructure>
</mod>
<num xmlns="http://docs.oasis-open.org/legaldocml/ns/akn/3.0">(2)</num>
<p xmlns="http://docs.oasis-open.org/legaldocml/ns/akn/3.0">On page 18, in Annex II, under point 2.1, the image of the upper part of the tyre label is replaced by the following:</p>
<p xmlns="http://docs.oasis-open.org/legaldocml/ns/akn/3.0"><!--default P | TXT --></p>
<num xmlns="http://docs.oasis-open.org/legaldocml/ns/akn/3.0">(3)</num>
<p xmlns="http://docs.oasis-open.org/legaldocml/ns/akn/3.0">On page 20, in Annex II, under point 2.1.4, the image of the bottom part of the tyre label is replaced by the following:</p>
<p xmlns="http://docs.oasis-open.org/legaldocml/ns/akn/3.0"><!--default P | TXT --></p>
<num xmlns="http://docs.oasis-open.org/legaldocml/ns/akn/3.0">(4)</num>
<p xmlns="http://docs.oasis-open.org/legaldocml/ns/akn/3.0">On page 21, in Annex II, point 2.2, point (e), 28th indent:</p>
<p xmlns="http://docs.oasis-open.org/legaldocml/ns/akn/3.0"><!--default P | TXT -->for:</p>
<mod xmlns="http://docs.oasis-open.org/legaldocml/ns/akn/3.0">
   <quotedStructure startQuote="" endQuote="">
      <p><!--default P | TXT -->&apos;snow grip pictogram: width 15 mm, height 13 mm, &lt;…&gt;&apos;,</p>
   </quotedStructure>
</mod>
<p xmlns="http://docs.oasis-open.org/legaldocml/ns/akn/3.0"><!--default P | TXT -->read:</p>
<mod xmlns="http://docs.oasis-open.org/legaldocml/ns/akn/3.0">
   <quotedStructure startQuote="" endQuote="">
      <p><!--default P | TXT -->&apos;snow grip pictogram: width 15 mm, height 14 mm, &lt;…&gt;&apos;.</p>
   </quotedStructure>
</mod>
