L2142021EN6810120210526EN0009681714<p xmlns="http://docs.oasis-open.org/legaldocml/ns/akn/3.0">Corrigendum to Commission Regulation (EU) 2021/850 of 26 May 2021 amending and correcting Annex II and amending Annexes III, IV and VI to Regulation (EC) No 1223/2009 of the European Parliament and of the Council on cosmetic products</p>
<p xmlns="http://docs.oasis-open.org/legaldocml/ns/akn/3.0">(Official Journal of the European Union L 188, 28 May 2021)</p>
<p xmlns="http://docs.oasis-open.org/legaldocml/ns/akn/3.0"><!--default P | TXT -->On page 44, the Annex to Regulation (EU) 2021/850 is replaced with the following</p>
<mod xmlns="http://docs.oasis-open.org/legaldocml/ns/akn/3.0">
   <quotedStructure startQuote="" endQuote="">
      <p><!--default P | TXT -->&apos;&apos;</p>
   </quotedStructure>
</mod>
