L3652021EN4610120210705EN0004461461<p xmlns="http://docs.oasis-open.org/legaldocml/ns/akn/3.0">Corrigendum to Commission Regulation (EU) 2021/1099 of 5 July 2021 amending Annexes II and III to Regulation (EC) No 1223/2009 of the European Parliament and of the Council on cosmetic products</p>
<p xmlns="http://docs.oasis-open.org/legaldocml/ns/akn/3.0">(Official Journal of the European Union L 238 of 6 July 2021)</p>On page 31, in the Annex, point (2), in the first column of the table:<p xmlns="http://docs.oasis-open.org/legaldocml/ns/akn/3.0"><!--default P | TXT -->for:</p>
<mod xmlns="http://docs.oasis-open.org/legaldocml/ns/akn/3.0">
   <quotedStructure startQuote="" endQuote="">
      <p><!--default P | TXT -->&apos;321&apos;,</p>
   </quotedStructure>
</mod>
<p xmlns="http://docs.oasis-open.org/legaldocml/ns/akn/3.0"><!--default P | TXT -->read:</p>
<mod xmlns="http://docs.oasis-open.org/legaldocml/ns/akn/3.0">
   <quotedStructure startQuote="" endQuote="">
      <p><!--default P | TXT -->&apos;322&apos;.</p>
   </quotedStructure>
</mod>
